[
    {
        "name": "1. Hane", 
        "time": {
            "unit": "sec", 
            "val": [
                0.0, 
                66.70581
            ]
        }
    }, 
    {
        "name": "Teslim", 
        "time": {
            "unit": "sec", 
            "val": [
                66.70581, 
                100.066141
            ]
        }
    }, 
    {
        "name": "2. Hane", 
        "time": {
            "unit": "sec", 
            "val": [
                100.066141, 
                166.766382
            ]
        }
    }, 
    {
        "name": "Teslim", 
        "time": {
            "unit": "sec", 
            "val": [
                166.766382, 
                200.088462
            ]
        }
    }
]