[
    {
        "name": "1. Hane", 
        "time": {
            "unit": "sec", 
            "val": [
                0.0, 
                83.377189
            ]
        }
    }, 
    {
        "name": "2. Hane", 
        "time": {
            "unit": "sec", 
            "val": [
                83.377189, 
                167.397779
            ]
        }
    }, 
    {
        "name": "3. Hane", 
        "time": {
            "unit": "sec", 
            "val": [
                167.397779, 
                251.002051
            ]
        }
    }, 
    {
        "name": "4. Hane", 
        "time": {
            "unit": "sec", 
            "val": [
                251.002051, 
                334.6875
            ]
        }
    }
]