[
    {
        "name": "1. Hane", 
        "time": {
            "unit": "sec", 
            "val": [
                0.0, 
                14.531426
            ]
        }
    }, 
    {
        "name": "Teslim", 
        "time": {
            "unit": "sec", 
            "val": [
                14.531426, 
                29.53287
            ]
        }
    }, 
    {
        "name": "2. Hane", 
        "time": {
            "unit": "sec", 
            "val": [
                29.53287, 
                44.103464
            ]
        }
    }, 
    {
        "name": "3. Hane", 
        "time": {
            "unit": "sec", 
            "val": [
                44.103464, 
                59.222414
            ]
        }
    }, 
    {
        "name": "4. Hane", 
        "time": {
            "unit": "sec", 
            "val": [
                59.222414, 
                131.25
            ]
        }
    }
]